Metadata-Version: 2.1
Name: dynamic-kobo
Version: 0.0.4
Summary: Replace / update / redeploy KoBo forms
Home-page: https://github.com/rodekruis/dynamic-kobo
Author: J. Margutti
Author-email: jmargutti@redcross.nl
License: UNKNOWN
Project-URL: Bug Reports, https://github.com/rodekruis/dynamic-kobo/issues
Project-URL: Source, https://github.com/rodekruis/dynamic-kobo
Keywords: KoBo
Platform: UNKNOWN
Classifier: Development Status :: 3 - Alpha
Classifier: License :: OSI Approved :: GNU Affero General Public License v3
Classifier: Programming Language :: Python :: 3
Classifier: Programming Language :: Python :: 3.7
Classifier: Programming Language :: Python :: 3.8
Classifier: Programming Language :: Python :: 3.9
Classifier: Programming Language :: Python :: 3.10
Classifier: Programming Language :: Python :: 3 :: Only
Requires-Python: >=3.7, <4
